mfd_hyperv/__init__.py
mfd_hyperv/base.py
mfd_hyperv/exceptions.py
mfd_hyperv/helpers.py
mfd_hyperv/hw_qos.py
mfd_hyperv/hypervisor.py
mfd_hyperv/vm_network_interface_manager.py
mfd_hyperv/vswitch_manager.py
mfd_hyperv/attributes/__init__.py
mfd_hyperv/attributes/vm_network_interface_attributes.py
mfd_hyperv/attributes/vm_params.py
mfd_hyperv/attributes/vm_processor_attributes.py
mfd_hyperv/attributes/vswitchattributes.py
mfd_hyperv/instances/__init__.py
mfd_hyperv/instances/vm.py
mfd_hyperv/instances/vm_network_interface.py
mfd_hyperv/instances/vswitch.py
mfd_hyperv-2.1.0.dist-info/licenses/AUTHORS.md
mfd_hyperv-2.1.0.dist-info/licenses/LICENSE.md
mfd_hyperv-2.1.0.dist-info/METADATA
mfd_hyperv-2.1.0.dist-info/WHEEL
mfd_hyperv-2.1.0.dist-info/top_level.txt
mfd_hyperv-2.1.0.dist-info/RECORD
