Metadata-Version: 2.4
Name: mfd-hyperv
Version: 2.1.0
Summary: Module for handling functionalities of HyperV hypervisor.
Project-URL: Homepage, https://github.com/intel/mfd
Project-URL: Repository, https://github.com/intel/mfd-hyperv
Project-URL: Issues, https://github.com/intel/mfd-hyperv/issues
Project-URL: Changelog, https://github.com/intel/mfd-hyperv/blob/main/CHANGELOG.md
Requires-Python: <3.14,>=3.10
License-File: LICENSE.md
License-File: AUTHORS.md
Requires-Dist: mfd-common-libs<2,>=1.11.0
Requires-Dist: mfd-typing<2,>=1.23.0
Requires-Dist: mfd_connect<8,>=7.12.0
Requires-Dist: mfd-ping<2,>=1.15.0
Requires-Dist: mfd_network_adapter<15,>=14.0.0
Dynamic: license-file
